src/defines.v
`ifndef _defines
`define _defines

// Functions

`define FN_ADD 6'h20
`define FN_SUB 6'h22
`define FN_AND 6'h24
`define FN_NOR 6'h27
`define FN_OR  6'h25
`define FN_XOR 6'h26
`define FN_SLL 6'h0
`define FN_SRL 6'h2
`define FN_SRA 6'h3
`define FN_SLT 6'h2a
`define FN_MUL 6'h18
`define FN_DIV 6'h1a
`define FN_JR  6'h8
`define FN_SYS 6'hc

// ALU operations

`define ALUOP_AND 4'h0
`define ALUOP_OR  4'h1
`define ALUOP_ADD 4'h2
`define ALUOP_NOR 4'h3
`define ALUOP_SLL 4'h4
`define ALUOP_SUB 4'h6
`define ALUOP_SLT 4'h7
`define ALUOP_SRL 4'h8
`define ALUOP_SRA 4'h9
`define ALUOP_XOR 4'ha
`define ALUOP_BEQ 4'hb
`define ALUOP_BNE 4'hc
`define ALUOP_LUI 4'hd
`define ALUOP_MUL 4'he
`define ALUOP_DIV 4'hf

// Opcodes

`define OP_RTYPE 6'h0
`define OP_ADDI  6'h8
`define OP_ANDI  6'hc
`define OP_ORI	 6'hd
`define OP_XORI	 6'he
`define OP_SLTI	 6'ha
`define OP_BEQ   6'h4
`define OP_BNE	 6'h5
`define OP_J     6'h2
`define OP_LB	 6'h20
`define OP_LUI	 6'hf
`define OP_LW    6'h23
`define OP_SB	 6'h28
`define OP_SW    6'h2b
`define OP_JAL   6'h3

`define SYS_PRINT_CHAR  11 
`define SYS_PRINT_INT    1
`define SYS_PRINT_FLOAT  2
`define SYS_READ_CHAR   12
`define SYS_READ_INT     5
`define SYS_READ_FLOAT   6
`define SYS_EXIT        10

`define IO_EXIT  8'hff
`define IO_CHAR  8'hfe
`define IO_INT   8'hfd
`define IO_FLOAT 8'hfc
`define IO_HEX   8'hfb

// Debug macros

`ifdef DEBUG
	`define DMSG(M) $display M ;
`else
	`define DMSG(M)
`endif

`define MEMORY_DATA "build/memory.raw"

`endif

src/memory.v
`ifndef _memory
`define _memory

`include "defines.v"

///////////////////////////////
//                           //
//           WIDTH           //
//        +---------->       //
//        | ........         //
//        | ........         //
//  DEPTH | ........         //
//        | ........         //
//        | ........         //
//        v                  //
//                           //
///////////////////////////////

module memory(
	input wire clk,
	input wire reset,
	input wire [ADDR-1:0] addr,
	input wire [WIDTH-1:0] wdata,
	input wire memwrite,
	input wire memread,
	output reg [WIDTH-1:0] rdata = {WIDTH{1'b0}}
);

parameter WIDTH = 128;
parameter DEPTH = 4; 
parameter ADDR = 32;
localparam WB = $clog2(WIDTH) - 3; // Width bits (address in bytes)
localparam DB = $clog2(DEPTH); // Depth bits

parameter DATA  = "build/memory.dat"; // Careful with this

// Unrolling for debug port
`ifdef DEBUG_MEMORY
wire [WIDTH*DEPTH-1:0] dbg_mem;
genvar j;
generate
for (j = 0; j < DEPTH; j = j + 1) begin
	assign dbg_mem[WIDTH*j+WIDTH-1:WIDTH*j] = mem[DEPTH-1-j];
end
endgenerate

initial begin
	$display("[MEMORY] Size: %d bytes", WIDTH * DEPTH / 8);
	$display("[MEMORY] Width: %d bits", WIDTH);
	$display("[MEMORY] Depth: %d lines", DEPTH);
	$display("[MEMORY] Address: %d bits", ADDR);
end
`endif

wire [DB-1:0] index;
assign index = addr[DB+WB-1:WB]; // Get whole line

reg [WIDTH-1:0] mem [0:DEPTH-1];

always @* begin
	if (memread && !reset) begin
		rdata <= mem[index];
	end
end

always @(posedge clk) begin
	if (reset) $readmemh(DATA, mem);
	else if (memwrite) begin
		mem[index] <= wdata;
	end
end

endmodule

`endif

test/memory_tb.v
`include "memory.v"
`include "defines.v"

// Memory Testbench
module memory_tb;

reg clk = 0;
reg reset = 0;
reg [31:0] addr = 32'b0;
reg memwrite = 0;
reg memread = 1;
wire [15:0] rdata;
reg [15:0] wdata;

always #5 clk = !clk;

memory #(
	.DATA("test/memory_tb.dat"),
	.WIDTH(16), .DEPTH(4)
) mem(
	.clk(clk),
	.reset(reset),
	.addr(addr),
	.rdata(rdata),
	.wdata(wdata),
	.memwrite(memwrite),
	.memread(memread)
);

initial begin
	`ifdef TRACEFILE
	$dumpfile(`TRACEFILE);
	$dumpvars(0, memory_tb);
	`endif

	$display("Clock    Address     Read");
	$display("-----    -------     ----");
	$monitor("%x        %x    %x", clk, addr, rdata);

	reset <= 1;
	# 10 reset <= 0;

	#2  addr <= 32'h00;
	#10 addr <= 32'h08;
	#10 addr <= 32'h10;
	#10 addr <= 32'h18;
	#10 begin
		memwrite <= 1;
		memread <= 0;
		addr <= 32'h00;
		wdata <= 16'h0;
	end
	#10 begin
		addr <= 32'h08;
		wdata <= 16'h1;
	end
	#10 begin
		addr <= 32'h10;
		wdata <= 16'h2;
	end
	#10 begin
		addr <= 32'h18;
		wdata <= 16'h3;
	end
	#10 begin
		addr <= 32'h00;
		memwrite <= 0;
		memread <= 1;
	end
	#10 addr <= 32'h08;
	#10 addr <= 32'h10;
	#10 addr <= 32'h18;
	#10 $finish;
end

endmodule

traces/memory.vcd
$date
	Fri Nov 13 21:19:24 2015
$end
$version
	Icarus Verilog
$end
$timescale
	1s
$end
$scope module memory_tb $end
$var wire 16 ! rdata [15:0] $end
$var reg 32 " addr [31:0] $end
$var reg 1 # clk $end
$var reg 1 $ memread $end
$var reg 1 % memwrite $end
$var reg 1 & reset $end
$var reg 16 ' wdata [15:0] $end
$scope module mem $end
$var wire 32 ( addr [31:0] $end
$var wire 1 ) clk $end
$var wire 64 * dbg_mem [63:0] $end
$var wire 2 + index [1:0] $end
$var wire 1 , memread $end
$var wire 1 - memwrite $end
$var wire 1 . reset $end
$var wire 16 / wdata [15:0] $end
$var reg 16 0 rdata [15:0] $end
$scope begin genblk1 $end
$upscope $end
$scope begin genblk01 $end
$upscope $end
$scope begin genblk001 $end
$upscope $end
$scope begin genblk0001 $end
$upscope $end
$upscope $end
$upscope $end
$enddefinitions $end
#0
$dumpvars
bx 0
bx /
1.
0-
1,
b0 +
bz *
0)
b0 (
bx '
1&
0%
1$
0#
b0 "
bx !
$end
#5
b10001001000100011001101000100010101010110011001110111 *
1#
1)
#10
b10001 0
b10001 !
0&
0.
0#
0)
#15
1#
1)
#20
0#
0)
#22
b1000 "
b1000 (
#25
1#
1)
#30
0#
0)
#32
b10001000110011 0
b10001000110011 !
b1 +
b10000 "
b10000 (
#35
1#
1)
#40
0#
0)
#42
b11000 "
b11000 (
#45
1#
1)
#50
0#
0)
#52
b0 +
b0 '
b0 /
b0 "
b0 (
0$
0,
1%
1-
#55
b1000100011001101000100010101010110011001110111 *
1#
1)
#60
0#
0)
#62
b1 '
b1 /
b1000 "
b1000 (
#65
b1001000100011001101000100010101010110011001110111 *
1#
1)
#70
0#
0)
#72
b1 +
b10 '
b10 /
b10000 "
b10000 (
#75
b1000000000000001001000100010101010110011001110111 *
1#
1)
#80
0#
0)
#82
b11 '
b11 /
b11000 "
b11000 (
#85
b1000000000000001101000100010101010110011001110111 *
1#
1)
#90
0#
0)
#92
b1 0
b1 !
b0 +
1$
1,
0%
0-
b0 "
b0 (
#95
1#
1)
#100
0#
0)
#102
b1000 "
b1000 (
#105
1#
1)
#110
0#
0)
#112
b11 0
b11 !
b1 +
b10000 "
b10000 (
#115
1#
1)
#120
0#
0)
#122
b11000 "
b11000 (
